{
  "main": {
    "id": "bff2efaec89a7f3f",
    "type": "split",
    "children": [
      {
        "id": "99ec728b4238b9ac",
        "type": "tabs",
        "children": [
          {
            "id": "df22d1eea46311b3",
            "type": "leaf",
            "state": {
              "type": "markdown",
              "state": {
                "file": "base model.md",
                "mode": "source",
                "source": false
              },
              "icon": "lucide-file",
              "title": "base model"
            }
          },
          {
            "id": "1f7d0c7325476a5f",
            "type": "leaf",
            "state": {
              "type": "markdown",
              "state": {
                "file": "Chronofold Whitepaper.md",
                "mode": "source",
                "source": false
              },
              "icon": "lucide-file",
              "title": "Chronofold Whitepaper"
            }
          }
        ],
        "currentTab": 1
      }
    ],
    "direction": "vertical"
  },
  "left": {
    "id": "64d57a3f854fd318",
    "type": "split",
    "children": [
      {
        "id": "4e5581d67ad16854",
        "type": "tabs",
        "children": [
          {
            "id": "c0232c09570d400b",
            "type": "leaf",
            "state": {
              "type": "file-explorer",
              "state": {
                "sortOrder": "alphabetical",
                "autoReveal": false
              },
              "icon": "lucide-folder-closed",
              "title": "Filutforskare"
            }
          },
          {
            "id": "3869cc5b1c691df8",
            "type": "leaf",
            "state": {
              "type": "search",
              "state": {
                "query": "",
                "matchingCase": false,
                "explainSearch": false,
                "collapseAll": false,
                "extraContext": false,
                "sortOrder": "alphabetical"
              },
              "icon": "lucide-search",
              "title": "Search"
            }
          },
          {
            "id": "4a0b76eab186f3ab",
            "type": "leaf",
            "state": {
              "type": "bookmarks",
              "state": {},
              "icon": "lucide-bookmark",
              "title": "Bookmarks"
            }
          }
        ]
      }
    ],
    "direction": "horizontal",
    "width": 300
  },
  "right": {
    "id": "ecffea5f9a95d99d",
    "type": "split",
    "children": [
      {
        "id": "c94c27c2922d7ded",
        "type": "tabs",
        "children": [
          {
            "id": "b81773151e7c913e",
            "type": "leaf",
            "state": {
              "type": "backlink",
              "state": {
                "file": "base model.md",
                "collapseAll": false,
                "extraContext": false,
                "sortOrder": "alphabetical",
                "showSearch": false,
                "searchQuery": "",
                "backlinkCollapsed": false,
                "unlinkedCollapsed": true
              },
              "icon": "links-coming-in",
              "title": "Backlinks for base model"
            }
          },
          {
            "id": "4976ab9a2fd6e4e6",
            "type": "leaf",
            "state": {
              "type": "outgoing-link",
              "state": {
                "file": "base model.md",
                "linksCollapsed": false,
                "unlinkedCollapsed": true
              },
              "icon": "links-going-out",
              "title": "Outgoing links from base model"
            }
          },
          {
            "id": "38868b88090c47b2",
            "type": "leaf",
            "state": {
              "type": "tag",
              "state": {
                "sortOrder": "frequency",
                "useHierarchy": true,
                "showSearch": false,
                "searchQuery": ""
              },
              "icon": "lucide-tags",
              "title": "Tags"
            }
          },
          {
            "id": "f69ae7a3c2592f25",
            "type": "leaf",
            "state": {
              "type": "all-properties",
              "state": {
                "sortOrder": "frequency",
                "showSearch": false,
                "searchQuery": ""
              },
              "icon": "lucide-archive",
              "title": "All properties"
            }
          },
          {
            "id": "77a3ce98eb75afd9",
            "type": "leaf",
            "state": {
              "type": "outline",
              "state": {
                "file": "base model.md",
                "followCursor": false,
                "showSearch": false,
                "searchQuery": ""
              },
              "icon": "lucide-list",
              "title": "Outline of base model"
            }
          }
        ]
      }
    ],
    "direction": "horizontal",
    "width": 300,
    "collapsed": true
  },
  "left-ribbon": {
    "hiddenItems": {
      "switcher:Öppna snabbväxlare": false,
      "graph:Öppna grafvy": false,
      "canvas:Skapa ny canvas": false,
      "daily-notes:Öppna dagens anteckning": false,
      "templates:Infoga mall": false,
      "command-palette:Öppna kommandopalett": false,
      "bases:Skapa ny bas": false
    }
  },
  "active": "1f7d0c7325476a5f",
  "lastOpenFiles": [
    "The future of AI.md",
    "Chronofold Whitepaper.md",
    "14aemjf3.pam~",
    "AI-rewrite of base model.md",
    "Namnlös.canvas",
    "Namnlös.base",
    "Welcome.md"
  ]
}